MANIFEST.in
distribute_setup.py
setup.py
./distribute_setup.py
./docs/conf.py
SimShop.egg-info/PKG-INFO
SimShop.egg-info/SOURCES.txt
SimShop.egg-info/dependency_links.txt
SimShop.egg-info/top_level.txt
bin/shop
docs/Makefile
docs/command_options.rst
docs/conf.py
docs/index.rst
docs/install.rst
docs/intro.rst
docs/quickstart.rst
docs/resource_file.rst
docs/sim_config.rst
simshop/EmailScoreBoard.py
simshop/Exceptions.py
simshop/NullHandler.py
simshop/Score.py
simshop/ScoreBoard.py
simshop/SimCfg.py
simshop/SimShopCfg.py
simshop/TestFind.py
simshop/__init__.py
simshop/archive.py
simshop/css_template.py
simshop/email_template.py
simshop/help.py
simshop/test_template.py
simshop/builders/CmdArgs.py
simshop/builders/CmdRun.py
simshop/builders/Exceptions.py
simshop/builders/HMS.py
simshop/builders/IcarusVerilog.py
simshop/builders/VerilogSim.py
simshop/builders/__init__.py