Metadata-Version: 1.0
Name: SimShop
Version: 0.15.4
Summary: Easy Verilog simulation
Home-page: http://pypi.python.org/pypi/SimShop
Author: Tim Weaver
Author-email: tim@rtlcores.com
License: LICENSE.txt
Platform: UNKNOWN
Classifier: Development Status :: 4 - Beta
Classifier: Environment :: Console
Classifier: Intended Audience :: End Users/Desktop
Classifier: Intended Audience :: Education
Classifier: License :: OSI Approved :: BSD License
Classifier: Operating System :: OS Independent
Classifier: Programming Language :: Python
Classifier: Topic :: Scientific/Engineering
Classifier: Topic :: Scientific/Engineering :: Electronic Design Automation (EDA)
Classifier: Topic :: Utilities
